conf/__init__.py
conf/backbone/rugpt3large.yaml
conf/backbone/rugpt3medium.yaml
conf/backbone/rugpt3small.yaml
conf/callbacks/freeze_transformer_unfreeze_prompt.yaml
conf/callbacks/reduce_checkpoint.yaml
conf/callbacks/save_pretrained_prompt.yaml
conf/callbacks/wb_log_hydra_config.yaml
conf/config.yaml
conf/dataset/default.yaml
conf/dataset/from_csv.yaml
conf/dataset/from_jsonl.yaml
conf/dataset/from_local.yaml
conf/dataset/from_tsv.yaml
conf/model/default.yaml
conf/model/gpt.yaml
conf/optimizer/adamw.yaml
conf/preprocessing/text2text.yaml
conf/prompt_format/default.yaml
conf/prompt_provider/lstm.yaml
conf/prompt_provider/tensor.yaml
conf/scheduler/cosine_annealing_warm_restarts.yaml
conf/scheduler/linear_schedule_with_warmup.yaml
conf/task/text2text.yaml
conf/tokenizer/autotokenizer.yaml
conf/tokenizer/rugpt3.yaml
conf/training/default.yaml
ruprompts/__init__.py
ruprompts/callbacks.py
ruprompts/cli/__init__.py
ruprompts/cli/train.py
ruprompts/pipelines.py
ruprompts/preprocessing.py
ruprompts/prompt.py
ruprompts/prompt_embedding.py
ruprompts/prompt_format.py
ruprompts/prompt_provider.py
ruprompts-0.1.4.dist-info/entry_points.txt
ruprompts-0.1.4.dist-info/LICENSE
ruprompts-0.1.4.dist-info/WHEEL
ruprompts-0.1.4.dist-info/METADATA
ruprompts-0.1.4.dist-info/RECORD
