Metadata-Version: 2.1
Name: ruprompts
Version: 0.1.4
Summary: Fast prompt tuning framework for large language models
Home-page: https://sberbank-ai.github.io/ru-prompts
License: Apache 2.0
Author: Sber AI
Author-email: nekonodyuk@sberbank.ru
Requires-Python: >=3.7,<4.0
Classifier: License :: Other/Proprietary License
Classifier: Programming Language :: Python :: 3
Classifier: Programming Language :: Python :: 3.7
Classifier: Programming Language :: Python :: 3.8
Classifier: Programming Language :: Python :: 3.9
Classifier: Programming Language :: Python :: 3.10
Classifier: Programming Language :: Python :: 3.11
Provides-Extra: hydra
Requires-Dist: datasets (>=1.16.1,<2.0.0); extra == "hydra"
Requires-Dist: hydra-core (>=1.1.0,<2.0.0); extra == "hydra"
Requires-Dist: torch (>=1.10.0,<2.0.0)
Requires-Dist: torchtyping (>=0.1.4,<0.2.0)
Requires-Dist: transformers (>=4.6.0,<5.0.0)
Requires-Dist: typeguard (>=2.13.3,<3.0.0)
Requires-Dist: typing-extensions (>=4.0.1,<5.0.0)
Project-URL: Documentation, https://sberbank-ai.github.io/ru-prompts
Project-URL: Repository, https://github.com/sberbank-ai/ru-prompts
